LICENSE
MANIFEST.in
README.md
pull_repos.py
setup.py
pull_repos.egg-info/PKG-INFO
pull_repos.egg-info/SOURCES.txt
pull_repos.egg-info/dependency_links.txt
pull_repos.egg-info/entry_points.txt
pull_repos.egg-info/top_level.txt