Metadata-Version: 1.1
Name: pull-repos
Version: 0.1.0
Summary: Pull and update repositories
Home-page: https://github.com/pikhovkin/pull-repos
Author: Sergei Pikhovkin
Author-email: s@pikhovkin.ru
License: MIT
Platform: UNKNOWN
Classifier: Development Status :: 5 - Production/Stable
Classifier: Intended Audience :: Developers
Classifier: License :: OSI Approved :: MIT License
Classifier: Programming Language :: Python :: 2.7
Classifier: Programming Language :: Python :: 3.6
Classifier: Programming Language :: Python :: 3.7
